gpyg/__init__.py
gpyg/gpg.py
gpyg/models/__init__.py
gpyg/models/card.py
gpyg/models/config.py
gpyg/models/infolines.py
gpyg/models/key.py
gpyg/models/key_editing.py
gpyg/operators/__init__.py
gpyg/operators/card.py
gpyg/operators/common.py
gpyg/operators/keys.py
gpyg/operators/messages.py
gpyg/util/__init__.py
gpyg/util/errors.py
gpyg/util/interactive.py
gpyg/util/process.py
gpyg-0.3.0.dist-info/METADATA
gpyg-0.3.0.dist-info/WHEEL
gpyg-0.3.0.dist-info/licenses/LICENSE
gpyg-0.3.0.dist-info/RECORD
