Metadata-Version: 2.3
Name: gpyg
Version: 0.3.0
Summary: A modern pythonic wrapper around GPG
Project-URL: Repository, https://github.com/iTecAI/GPyG
Project-URL: Documentation, https://itecai.github.io/GPyG
Author: Dax Harris
License: MIT License
License-File: LICENSE
Keywords: cryptography,gpg,pgp
Classifier: Programming Language :: Python
Requires-Python: >=3.12
Requires-Dist: pydantic
Requires-Dist: typing-extensions
Provides-Extra: dev
Requires-Dist: mkdocs; extra == 'dev'
Requires-Dist: mkdocstrings[python]; extra == 'dev'
Requires-Dist: pytest; extra == 'dev'
